odoo10_addon_business_requirement_deliverable_resource_template_categ-10.0.1.1.0-py2.7-nspkg.pth
odoo/addons/business_requirement_deliverable_resource_template_categ/README.rst
odoo/addons/business_requirement_deliverable_resource_template_categ/__init__.py
odoo/addons/business_requirement_deliverable_resource_template_categ/__manifest__.py
odoo/addons/business_requirement_deliverable_resource_template_categ/data/business_requirement_deliverable_resource_template_categ_demo.xml
odoo/addons/business_requirement_deliverable_resource_template_categ/i18n/es.po
odoo/addons/business_requirement_deliverable_resource_template_categ/i18n/sl.po
odoo/addons/business_requirement_deliverable_resource_template_categ/models/__init__.py
odoo/addons/business_requirement_deliverable_resource_template_categ/models/business_requirement_resource_template.py
odoo/addons/business_requirement_deliverable_resource_template_categ/static/description/icon.png
odoo/addons/business_requirement_deliverable_resource_template_categ/static/img/bus_req_default.png
odoo/addons/business_requirement_deliverable_resource_template_categ/static/img/bus_req_default2.png
odoo/addons/business_requirement_deliverable_resource_template_categ/views/business_requirement_resource_template.xml
odoo10_addon_business_requirement_deliverable_resource_template_categ-10.0.1.1.0.dist-info/DESCRIPTION.rst
odoo10_addon_business_requirement_deliverable_resource_template_categ-10.0.1.1.0.dist-info/METADATA
odoo10_addon_business_requirement_deliverable_resource_template_categ-10.0.1.1.0.dist-info/RECORD
odoo10_addon_business_requirement_deliverable_resource_template_categ-10.0.1.1.0.dist-info/WHEEL
odoo10_addon_business_requirement_deliverable_resource_template_categ-10.0.1.1.0.dist-info/metadata.json
odoo10_addon_business_requirement_deliverable_resource_template_categ-10.0.1.1.0.dist-info/namespace_packages.txt
odoo10_addon_business_requirement_deliverable_resource_template_categ-10.0.1.1.0.dist-info/top_level.txt
