Metadata-Version: 2.0
Name: odoo10-addon-business-requirement-deliverable-resource-template-categ
Version: 10.0.1.1.0
Summary: Manage default resource lines categories in your
Home-page: https://www.elico-corp.com/
Author: Elico Corp, Odoo Community Association (OCA)
Author-email: support@odoo-community.org
License: AGPL-3
Platform: UNKNOWN
Classifier: Programming Language :: Python
Classifier: Framework :: Odoo
Classifier: License :: OSI Approved :: GNU Affero General Public License v3
Requires-Python: ~=2.7
Requires-Dist: odoo (<10.1dev,>=10.0)
Requires-Dist: odoo10-addon-business-requirement-deliverable-project-task-categ
Requires-Dist: odoo10-addon-business-requirement-deliverable-resource-template
